pytest_wiremock/__init__.py
pytest_wiremock/client/__init__.py
pytest_wiremock/client/_client.py
pytest_wiremock/client/_constants.py
pytest_wiremock/client/_decorators.py
pytest_wiremock/client/_exceptions.py
pytest_wiremock/client/_protocols.py
pytest_wiremock/client/_response.py
pytest_wiremock/client/_types.py
pytest_wiremock/client/endpoints/__init__.py
pytest_wiremock/client/endpoints/near_misses.py
pytest_wiremock/client/endpoints/recordings.py
pytest_wiremock/client/endpoints/requests.py
pytest_wiremock/client/endpoints/scenarios.py
pytest_wiremock/client/endpoints/stubs.py
pytest_wiremock/client/endpoints/system.py
pytest_wiremock/client/resources/__init__.py
pytest_wiremock/client/resources/models.py
pytest_wiremock/client/resources/schemas.py
pytest_wiremock/dsl/__init__.py
pytest_wiremock/dsl/builder.py
pytest_wiremock/dsl/method_conditions.py
pytest_wiremock/plugin.py
pytest_wiremock/py.typed
pytest_wiremock-0.1.0.dist-info/entry_points.txt
pytest_wiremock-0.1.0.dist-info/LICENSE
pytest_wiremock-0.1.0.dist-info/WHEEL
pytest_wiremock-0.1.0.dist-info/METADATA
pytest_wiremock-0.1.0.dist-info/RECORD
